3219a501864e4a26eb38__mypyc.cpython-310-darwin.so
crossandra/rule.cpython-310-darwin.so
crossandra/lib.py
crossandra/common.cpython-310-darwin.so
crossandra/__init__.py
crossandra/__init__.cpython-310-darwin.so
crossandra/rule.py
crossandra/common.py
crossandra/py.typed
crossandra/exceptions.py
crossandra/lib.cpython-310-darwin.so
crossandra-2.2.1.dist-info/RECORD
crossandra-2.2.1.dist-info/LICENSE
crossandra-2.2.1.dist-info/WHEEL
crossandra-2.2.1.dist-info/top_level.txt
crossandra-2.2.1.dist-info/METADATA
