Metadata-Version: 2.1
Name: crossandra
Version: 2.2.1
Summary: A fast and simple enum/regex-based tokenizer with decent configurability
Author-email: trag1c <trag1cdev@yahoo.com>
License: MIT
Project-URL: repository, https://github.com/trag1c/crossandra
Requires-Python: >=3.8
License-File: LICENSE
Requires-Dist: result~=0.9.0
